pinthesky/__init__.py
pinthesky/__main__.py
pinthesky/camera.py
pinthesky/cloudwatch.py
pinthesky/combiner.py
pinthesky/config.py
pinthesky/connection.py
pinthesky/conversion.py
pinthesky/events.py
pinthesky/handler.py
pinthesky/health.py
pinthesky/input.py
pinthesky/motion_detect.py
pinthesky/output.py
pinthesky/session.py
pinthesky/upload.py
pinthesky-0.9.0.dist-info/LICENSE
pinthesky-0.9.0.dist-info/METADATA
pinthesky-0.9.0.dist-info/WHEEL
pinthesky-0.9.0.dist-info/entry_points.txt
pinthesky-0.9.0.dist-info/top_level.txt
pinthesky-0.9.0.dist-info/RECORD
