Metadata-Version: 2.1
Name: pinthesky
Version: 0.9.0
Summary: Simple Pi In The Sky device Integration
Home-page: https://github.com/philcali/pits-device
Author: Philip Cali
Author-email: philip.cali@gmail.com
License: Apache License 2.0
Classifier: Programming Language :: Python :: 3
Classifier: Programming Language :: Python :: 3.8
Classifier: Programming Language :: Python :: 3.9
Classifier: Programming Language :: Python :: 3.10
Classifier: Programming Language :: Python :: 3.11
Classifier: Programming Language :: Python :: 3.12
Classifier: License :: OSI Approved :: Apache Software License
Classifier: Operating System :: OS Independent
License-File: LICENSE
Requires-Dist: boto3
Requires-Dist: requests
Requires-Dist: numpy
Requires-Dist: inotify-simple
Requires-Dist: picamera
Requires-Dist: psutil
Provides-Extra: test
Requires-Dist: pytest ; extra == 'test'
Requires-Dist: requests-mock ; extra == 'test'
